teon/__init__.py
teon/attributes.py
teon/audio.py
teon/camera.py
teon/collider.py
teon/core.py
teon/entity.py
teon/functions.py
teon/level.py
teon/mouse.py
teon/other.py
teon/renderer.py
teon/setup.py
teon/shader.py
teon/text.py
teon/time.py
teon/widget.py
teon/window.py
teon-0.6.0.dist-info/METADATA
teon-0.6.0.dist-info/WHEEL
teon-0.6.0.dist-info/top_level.txt
teon-0.6.0.dist-info/RECORD
