Metadata-Version: 2.1
Name: teon
Version: 0.6.0
Summary: A simple, beginner-friendly 2D game engine using Pygame and ModernGL
Author: Mihailo D (YT: @NotMihax)
Author-email: mickeyyess2@gmail.com
Keywords: game engine pygame moderngl 2d simple
Requires-Dist: pygame
Requires-Dist: Pillow
Requires-Dist: moderngl
Requires-Dist: numpy
